MANIFEST.in
README.md
setup.cfg
setup.py
public/__init__.py
public/alert.py
public/communicate.py
public/configure.py
public/formular.py
public/lextab.py
public/logger.py
public/mail_server.py
public/pubsub.py
public/sms.py
skyconf/__init__.py
skyconf/init_db.py
skyline_client/__init__.py
skyline_client/__main__.py
skyline_client/client.py
skyline_client/filter.py
skyline_client/gather.py
skyline_client/matcher.py
skyline_client/monitor_worker.py
skyline_client/summary_worker.py
skyline_client/verify.py
skyline_client/warning_worker.py
skyline_client/worker.py
skymonitor.egg-info/PKG-INFO
skymonitor.egg-info/SOURCES.txt
skymonitor.egg-info/dependency_links.txt
skymonitor.egg-info/entry_points.txt
skymonitor.egg-info/pbr.json
skymonitor.egg-info/requires.txt
skymonitor.egg-info/top_level.txt
test/test_read.py
test/test_write.py