Metadata-Version: 1.1
Name: skymonitor
Version: 0.0.16
Summary: skyline monitor
Home-page: https://github.com/xiachufang/skyline
Author: liuweibo
Author-email: liuweibo@xiachufang.com
License: MIT
Keywords: skyline monitor
Platform: UNKNOWN
Classifier: Development Status :: 3 - Alpha
Classifier: License :: OSI Approved :: MIT License
Classifier: Natural Language :: Chinese (Simplified)
Classifier: Programming Language :: Python :: 2
Classifier: Programming Language :: Python :: 2.6
Classifier: Programming Language :: Python :: 2.7
Classifier: Programming Language :: Python :: 3.3
Classifier: Programming Language :: Python :: 3.4
